[
  {
    "title": "单边主义没有未来",
    "author": "作者-钟声",
    "from": "人民日报",
    "date": "06-24"
  },
  {
    "title": "扶贫，从“新手”到“熟路”",
    "author": "作者-黄文秀",
    "from": "光明日报",
    "date": "06-24"
  },
  {
    "title": "走好乡村善治之路",
    "author": "作者-农兴",
    "from": "经济日报",
    "date": "06-24"
  },
  {
    "title": "紧扣“严”字砺英才",
    "author": "作者-汤俊峰 胡杨",
    "from": "解放军报",
    "date": "06-24"
  },
  {
    "title": "闻过则喜 知过不讳",
    "author": "作者-王李彬",
    "from": "中国纪检监察报",
    "date": "06-24"
  },
  {
    "title": "努力进入历史情境",
    "author": "作者-周良书",
    "from": "北京日报",
    "date": "06-24"
  },
  {
    "title": "“法与时转”与“因俗而治”",
    "author": "作者-张晋藩",
    "from": "北京日报",
    "date": "06-24"
  },
  {
    "title": "敢于斗争才能赢得尊严",
    "author": "作者-华宁",
    "from": "人民日报",
    "date": "06-25"
  },
  {
    "title": "血与火考验伴随始终",
    "author": "作者-米博华",
    "from": "中国纪检监察报",
    "date": "06-24"
  },
  {
    "title": "坚守初心使命 认真履职尽责",
    "author": "作者-评论员 聂新鑫",
    "from": "中国纪检监察报",
    "date": "06-24"
  },
  {
    "title": "干事创业莫学曾参",
    "author": "作者-匡吉",
    "from": "解放军报",
    "date": "06-24"
  },
  {
    "title": "挖掘释放贸易对扩大就业的潜力",
    "author": "作者-赵瑾",
    "from": "经济日报",
    "date": "06-24"
  },
  {
    "title": "理性看待互联网平台垄断",
    "author": "作者-熊鸿儒",
    "from": "经济日报",
    "date": "06-24"
  },
  {
    "title": "英国自然风景园的形成及发展",
    "author": "作者-赵晶",
    "from": "光明日报",
    "date": "06-24"
  },
  {
    "title": "G20科技创新：以开放合作助力机制化建设",
    "author": "作者-黄茂兴",
    "from": "光明日报",
    "date": "06-24"
  },
  {
    "title": "意大利文艺复兴时期的风景园林",
    "author": "作者-于冰沁",
    "from": "光明日报",
    "date": "06-24"
  },
  {
    "title": "法国古典主义园林的兴衰",
    "author": "作者-杨鑫",
    "from": "光明日报",
    "date": "06-24"
  },
  {
    "title": "中国应对贸易摩擦的国际公共产品",
    "author": "作者-魏亮",
    "from": "光明日报",
    "date": "06-24"
  },
  {
    "title": "用共赢的理念应对老龄化社会的新问题",
    "author": "作者-李勤余",
    "from": "光明日报",
    "date": "06-24"
  },
  {
    "title": "愿每个“儿童主任”都有慈母般的眼睛",
    "author": "作者-王石川",
    "from": "光明日报",
    "date": "06-24"
  },
  {
    "title": "以协调、合作、稳定为基调推进中美关系发展",
    "author": "作者-刁大明",
    "from": "光明日报",
    "date": "06-24"
  },
  {
    "title": "发挥网络优势 助力脱贫攻坚",
    "author": "作者-谷业凯",
    "from": "人民日报",
    "date": "06-24"
  },
  {
    "title": "当代中国经济学成长壮大的主要路径",
    "author": "作者-石建勋",
    "from": "人民日报",
    "date": "06-24"
  },
  {
    "title": "不断完善中国特色收入分配理论",
    "author": "作者-权衡",
    "from": "人民日报",
    "date": "06-24"
  },
  {
    "title": "成本降下来，质量提上去",
    "author": "作者-陆娅楠",
    "from": "人民日报",
    "date": "06-24"
  },
  {
    "title": "集智攻关无不成",
    "author": "作者-彭飞",
    "from": "人民日报",
    "date": "06-24"
  },
  {
    "title": "探索两岸融合发展新路",
    "author": "作者-禾立",
    "from": "人民日报",
    "date": "06-23"
  },
  {
    "title": "为亚洲打造开启美好未来的钥匙",
    "author": "作者-李莞梅",
    "from": "解放军报",
    "date": "06-23"
  },
  {
    "title": "新时代中国博物馆的新使命",
    "author": "作者-杨程斌",
    "from": "光明日报",
    "date": "06-23"
  },
  {
    "title": "两岸交流融合势不可挡",
    "author": "作者-廉丹",
    "from": "经济日报",
    "date": "06-23"
  },
  {
    "title": "勤学习善思考信其道用其理",
    "author": "作者-桑林峰",
    "from": "中国纪检监察报",
    "date": "06-23"
  },
  {
    "title": "共同开启中朝友谊崭新篇章",
    "author": "作者-新华社评论员",
    "from": "新华每日电讯",
    "date": "06-22"
  },
  {
    "title": "只有平等对话才能实现互利共赢",
    "author": "作者-五月荷",
    "from": "人民日报",
    "date": "06-22"
  },
  {
    "title": "全球化是不可阻挡的历史潮流",
    "author": "作者-孙学工",
    "from": "经济日报",
    "date": "06-22"
  },
  {
    "title": "从严整改落实",
    "author": "匿名",
    "from": "解放军报",
    "date": "06-22"
  },
  {
    "title": "擘画中朝关系美好未来",
    "author": "作者-吴晶晶",
    "from": "人民日报海外版",
    "date": "06-22"
  },
  {
    "title": "风展红旗如画",
    "author": "作者-记者 谢良 刘斐 陈弘毅 等",
    "from": "新华网",
    "date": "06-21"
  },
  {
    "title": "不忘初心　携手前进",
    "author": "作者-任寰宇",
    "from": "人民日报",
    "date": "06-21"
  },
  {
    "title": "读懂忠诚和初心的时代内涵",
    "author": "作者-王传宝",
    "from": "光明日报",
    "date": "06-21"
  },
  {
    "title": "既要旗帜鲜明也要润物无声",
    "author": "作者-杜中武 郭永利",
    "from": "解放军报",
    "date": "06-21"
  },
  {
    "title": "政治洗礼　固本培元",
    "author": "作者-魏寅",
    "from": "中国纪检监察报",
    "date": "06-21"
  },
  {
    "title": "把科创板建设好发展好",
    "author": "作者-午言",
    "from": "人民日报",
    "date": "06-21"
  },
  {
    "title": "弘扬践行黄大年精神着力培养时代新人",
    "author": "作者-杨振斌",
    "from": "光明日报",
    "date": "06-21"
  },
  {
    "title": "美国挑起的经贸摩擦破坏世界经济体系",
    "author": "作者-记者 韩鑫 车斌",
    "from": "人民日报",
    "date": "06-21"
  },
  {
    "title": "文艺工作要讲真情实意",
    "author": "作者-郑乐秋",
    "from": "光明日报",
    "date": "06-21"
  },
  {
    "title": "重温入党誓词牢记初心使命",
    "author": "作者-李慎明",
    "from": "光明日报",
    "date": "06-21"
  },
  {
    "title": "为“上海精神”注入新内涵",
    "author": "作者-记者 袁勇",
    "from": "经济日报",
    "date": "06-21"
  },
  {
    "title": "走好新时代长征路",
    "author": "作者-赵淑兰",
    "from": "经济日报",
    "date": "06-21"
  },
  {
    "title": "今年夏粮丰收意义重大",
    "author": "作者-乔金亮",
    "from": "经济日报",
    "date": "06-21"
  },
  {
    "title": "全球化势不可挡　贸易战没有赢家",
    "author": "作者-记者 徐惠喜 仇莉娜",
    "from": "经济日报",
    "date": "06-21"
  }
]